ac_mcp_server/__init__.py
ac_mcp_server/ac_client.py
ac_mcp_server/server.py
ac_mcp_server/tools.py
ac_mcp_server/types.py
ac_mcp_server/utils.py
ac_mcp_server-0.12.0.dist-info/METADATA
ac_mcp_server-0.12.0.dist-info/WHEEL
ac_mcp_server-0.12.0.dist-info/entry_points.txt
ac_mcp_server-0.12.0.dist-info/RECORD
