Metadata-Version: 2.4
Name: ac-mcp-server
Version: 0.12.0
Summary: Official ActiveCampaign MCP Server
Project-URL: Homepage, https://activecampaign.com
Project-URL: Documentation, https://activecampaign.com/mcp
License-Expression: MIT
Keywords: ac,activecampaign,mcp,mcp-server
Classifier: Development Status :: 4 - Beta
Classifier: Intended Audience :: Developers
Classifier: Programming Language :: Python :: 3
Classifier: Programming Language :: Python :: 3.13
Requires-Python: >=3.10
Requires-Dist: fastmcp>=2.10.4
Requires-Dist: requests>=2.32.3
